videocutter/__init__.py
videocutter/__main__.py
videocutter/videocutter.py
videocutter-2024.12.17.1.dist-info/METADATA
videocutter-2024.12.17.1.dist-info/WHEEL
videocutter-2024.12.17.1.dist-info/entry_points.txt
videocutter-2024.12.17.1.dist-info/licenses/LICENCE
videocutter-2024.12.17.1.dist-info/RECORD
