Metadata-Version: 2.4
Name: videocutter
Version: 2024.12.17.1
Summary: Split videos around time points.
Project-URL: Homepage, https://github.com/TeamNCMC/videocutter
Project-URL: Source Code, https://github.com/TeamNCMC/videocutter
Project-URL: Bug Tracker, https://github.com/TeamNCMC/videocutter/issues
Author-email: Guillaume Le Goc <g.legoc@posteo.org>
License: MIT
License-File: LICENCE
Classifier: Programming Language :: Python :: 3.12
Requires-Python: >=3.12
Requires-Dist: numpy>=2.1
Requires-Dist: pandas>=2.2.3
Requires-Dist: tqdm
Requires-Dist: typer
